__init__.py
8x_esystem_reports_data_warehouse_api_python_sdk-1.0.0.dist-info/licenses/LICENSE
oitoxesystem/__init__.py
oitoxesystem/reportsdatawarehouseapi/__init__.py
oitoxesystem/reportsdatawarehouseapi/api.py
oitoxesystem/reportsdatawarehouseapi/apis/__init__.py
oitoxesystem/reportsdatawarehouseapi/apis/fuel_suplly_record.py
oitoxesystem/reportsdatawarehouseapi/apis/kilometer_tracker.py
oitoxesystem/reportsdatawarehouseapi/apis/working_day.py
8x_esystem_reports_data_warehouse_api_python_sdk-1.0.0.dist-info/METADATA
8x_esystem_reports_data_warehouse_api_python_sdk-1.0.0.dist-info/WHEEL
8x_esystem_reports_data_warehouse_api_python_sdk-1.0.0.dist-info/top_level.txt
8x_esystem_reports_data_warehouse_api_python_sdk-1.0.0.dist-info/RECORD
